flora_opt/__init__.py
flora_opt/optimizers/__init__.py
flora_opt/optimizers/optax/__init__.py
flora_opt/optimizers/optax/flora.py
flora_opt/optimizers/optax/utils.py
flora_opt/optimizers/torch/__init__.py
flora_opt/optimizers/torch/flora.py
flora_opt-0.0.3.dist-info/LICENSE
flora_opt-0.0.3.dist-info/LICENSE.GPL
flora_opt-0.0.3.dist-info/METADATA
flora_opt-0.0.3.dist-info/WHEEL
flora_opt-0.0.3.dist-info/top_level.txt
flora_opt-0.0.3.dist-info/RECORD
