Metadata-Version: 2.1
Name: flora-opt
Version: 0.0.3
Author: Yongchang Hao
License-File: LICENSE
License-File: LICENSE.GPL
Provides-Extra: jax
Requires-Dist: optax ; extra == 'jax'
Requires-Dist: flax ; extra == 'jax'
Requires-Dist: jax ; extra == 'jax'
Provides-Extra: testing
Requires-Dist: pytest ; extra == 'testing'
Requires-Dist: pytest-cov ; extra == 'testing'
Provides-Extra: torch
Requires-Dist: torch ; extra == 'torch'
Requires-Dist: bitsandbytes ; extra == 'torch'
Requires-Dist: accelerate ; extra == 'torch'
